testmodule3091/__init__.py
testmodule3091/cssbuilder.py
testmodule3091/director.py
testmodule3091/docxbuilder.py
testmodule3091/docxconstructor.py
testmodule3091/htmlbuilder.py
testmodule3091/jsonbuilder.py
testmodule3091/loadsetup.py
testmodule3091/oddprocessor.py
testmodule3091/pathvalidator.py
testmodule3091/teiauxiliary.py
testmodule3091/teitransformer.py
testmodule3091/teixml.py
testmodule3091/xmlvalidators.py
testmodule3091/data/.DS_Store
testmodule3091/data/config/docx_constructor.yaml
testmodule3091/data/config/html_transformer.yaml
testmodule3091/data/config/tei_transformer.yaml
testmodule3091/data/css/.DS_Store
testmodule3091/data/css/base/.DS_Store
testmodule3091/data/css/drama/.DS_Store
testmodule3091/data/css/drama/docx/drama.css
testmodule3091/data/css/drama/html/drama.css
testmodule3091/data/css/plain/.DS_Store
testmodule3091/data/css/plain/docx/plain.css
testmodule3091/data/css/plain/html/.DS_Store
testmodule3091/data/css/plain/html/plain.css
testmodule3091/data/schema/.DS_Store
testmodule3091/data/schema/scenarios/.DS_Store
testmodule3091/data/schema/scenarios/drama/.DS_Store
testmodule3091/data/schema/scenarios/drama/dtd/tei_drama.dtd
testmodule3091/data/schema/scenarios/drama/rng/.DS_Store
testmodule3091/data/schema/scenarios/drama/rng/tei_drama.rng
testmodule3091/data/schema/scenarios/drama/xsd/.DS_Store
testmodule3091/data/schema/scenarios/drama/xsd/tei_drama.xsd
testmodule3091/data/schema/scenarios/drama/xsd/tei_drama_dcr.xsd
testmodule3091/data/schema/scenarios/drama/xsd/tei_drama_xml.xsd
testmodule3091/data/schema/scenarios/plain/.DS_Store
testmodule3091/data/schema/scenarios/plain/dtd/.DS_Store
testmodule3091/data/schema/scenarios/plain/dtd/plain.dtd
testmodule3091/data/schema/scenarios/plain/rng/.DS_Store
testmodule3091/data/schema/scenarios/plain/rng/plain.rng
testmodule3091/data/schema/scenarios/plain/xsd/.DS_Store
testmodule3091/data/schema/scenarios/plain/xsd/plain.xsd
testmodule3091/data/templates/document.html
testmodule3091-0.3.4.dist-info/METADATA
testmodule3091-0.3.4.dist-info/WHEEL
testmodule3091-0.3.4.dist-info/top_level.txt
testmodule3091-0.3.4.dist-info/RECORD
